cyclopts/__init__.py
cyclopts/__init__.pyi
cyclopts/__main__.py
cyclopts/_convert.py
cyclopts/_edit.py
cyclopts/_env_var.py
cyclopts/_markup.py
cyclopts/_result_action.py
cyclopts/_run.py
cyclopts/_version.py
cyclopts/annotations.py
cyclopts/app_stack.py
cyclopts/bind.py
cyclopts/command_spec.py
cyclopts/core.py
cyclopts/exceptions.py
cyclopts/field_info.py
cyclopts/group.py
cyclopts/group_extractors.py
cyclopts/loader.py
cyclopts/panel.py
cyclopts/parameter.py
cyclopts/protocols.py
cyclopts/py.typed
cyclopts/sphinx_ext.py
cyclopts/token.py
cyclopts/types.py
cyclopts/utils.py
cyclopts/argument/__init__.py
cyclopts/argument/_argument.py
cyclopts/argument/_collection.py
cyclopts/argument/utils.py
cyclopts/cli/__init__.py
cyclopts/cli/_complete.py
cyclopts/cli/docs.py
cyclopts/cli/run.py
cyclopts/completion/__init__.py
cyclopts/completion/_base.py
cyclopts/completion/bash.py
cyclopts/completion/detect.py
cyclopts/completion/fish.py
cyclopts/completion/install.py
cyclopts/completion/zsh.py
cyclopts/config/__init__.py
cyclopts/config/_common.py
cyclopts/config/_env.py
cyclopts/config/_json.py
cyclopts/config/_toml.py
cyclopts/config/_yaml.py
cyclopts/docs/__init__.py
cyclopts/docs/base.py
cyclopts/docs/html.py
cyclopts/docs/markdown.py
cyclopts/docs/rst.py
cyclopts/docs/types.py
cyclopts/ext/__init__.py
cyclopts/ext/mkdocs.py
cyclopts/ext/sphinx.py
cyclopts/help/__init__.py
cyclopts/help/help.py
cyclopts/help/inline_text.py
cyclopts/help/protocols.py
cyclopts/help/rst_preprocessor.py
cyclopts/help/silent.py
cyclopts/help/specs.py
cyclopts/help/formatters/__init__.py
cyclopts/help/formatters/default.py
cyclopts/help/formatters/html.py
cyclopts/help/formatters/markdown.py
cyclopts/help/formatters/plain.py
cyclopts/help/formatters/rst.py
cyclopts/validators/__init__.py
cyclopts/validators/_group.py
cyclopts/validators/_number.py
cyclopts/validators/_path.py
cyclopts-4.4.2.dist-info/METADATA
cyclopts-4.4.2.dist-info/WHEEL
cyclopts-4.4.2.dist-info/entry_points.txt
cyclopts-4.4.2.dist-info/licenses/LICENSE
cyclopts-4.4.2.dist-info/RECORD
