Metadata-Version: 2.4
Name: cyclopts
Version: 4.4.2
Summary: Intuitive, easy CLIs based on type hints.
Project-URL: Homepage, https://github.com/BrianPugh/cyclopts
Project-URL: Repository, https://github.com/BrianPugh/cyclopts
Author: Brian Pugh
License-Expression: Apache-2.0
License-File: LICENSE
Classifier: License :: OSI Approved :: Apache Software License
Classifier: Operating System :: OS Independent
Classifier: Programming Language :: Python :: 3
Classifier: Programming Language :: Python :: 3.10
Classifier: Programming Language :: Python :: 3.11
Classifier: Programming Language :: Python :: 3.12
Classifier: Programming Language :: Python :: 3.13
Requires-Python: >=3.10
Requires-Dist: attrs>=23.1.0
Requires-Dist: docstring-parser<4.0,>=0.15
Requires-Dist: rich-rst<2.0.0,>=1.3.1
Requires-Dist: rich>=13.6.0
Requires-Dist: tomli>=2.0.0; python_version < '3.11'
Requires-Dist: typing-extensions>=4.8.0; python_version < '3.11'
Provides-Extra: debug
Requires-Dist: ipdb>=0.13.9; extra == 'debug'
Requires-Dist: line-profiler>=3.5.1; extra == 'debug'
Provides-Extra: dev
Requires-Dist: coverage[toml]>=5.1; extra == 'dev'
Requires-Dist: mkdocs>=1.4.0; extra == 'dev'
Requires-Dist: pre-commit>=2.16.0; extra == 'dev'
Requires-Dist: pydantic<3.0.0,>=2.11.2; extra == 'dev'
Requires-Dist: pytest-cov>=3.0.0; extra == 'dev'
Requires-Dist: pytest-mock>=3.7.0; extra == 'dev'
Requires-Dist: pytest>=8.2.0; extra == 'dev'
Requires-Dist: pyyaml>=6.0.1; extra == 'dev'
Requires-Dist: syrupy>=4.0.0; extra == 'dev'
Requires-Dist: toml<1.0.0,>=0.10.2; extra == 'dev'
Requires-Dist: trio>=0.10.0; extra == 'dev'
Provides-Extra: docs
Requires-Dist: gitpython>=3.1.31; extra == 'docs'
Requires-Dist: myst-parser[linkify]<5.0.0,>=3.0.1; extra == 'docs'
Requires-Dist: sphinx-autodoc-typehints<4.0.0,>=1.25.2; extra == 'docs'
Requires-Dist: sphinx-copybutton<1.0,>=0.5; extra == 'docs'
Requires-Dist: sphinx-rtd-dark-mode<2.0.0,>=1.3.0; extra == 'docs'
Requires-Dist: sphinx-rtd-theme<4.0.0,>=3.0.0; extra == 'docs'
Requires-Dist: sphinx<8.2.0,>=7.4.7; extra == 'docs'
Provides-Extra: mkdocs
Requires-Dist: markdown>=3.3; extra == 'mkdocs'
Requires-Dist: mkdocs>=1.4.0; extra == 'mkdocs'
Requires-Dist: pymdown-extensions>=10.0; extra == 'mkdocs'
Provides-Extra: toml
Requires-Dist: tomli>=2.0.0; (python_version < '3.11') and extra == 'toml'
Provides-Extra: trio
Requires-Dist: trio>=0.10.0; extra == 'trio'
Provides-Extra: yaml
Requires-Dist: pyyaml>=6.0.1; extra == 'yaml'
